solvesudoku/__init__.py
solvesudoku-0.0.3.dist-info/LICENSE
solvesudoku-0.0.3.dist-info/METADATA
solvesudoku-0.0.3.dist-info/WHEEL
solvesudoku-0.0.3.dist-info/top_level.txt
solvesudoku-0.0.3.dist-info/RECORD
