Metadata-Version: 2.1
Name: solvesudoku
Version: 0.0.3
Summary: Solves Sudoku within seconds.
Home-page: https://github.com/Raj-Srikar/solvesudoku
Author: Raj Srikar
Author-email: rajsrikar.d161@gmail.com
License: UNKNOWN
Project-URL: Documentation, https://github.com/Raj-Srikar/solvesudoku/wiki#documentation
Platform: UNKNOWN
Classifier: Programming Language :: Python :: 3
Classifier: License :: OSI Approved :: MIT License
Classifier: Operating System :: OS Independent
Requires-Python: >=3.6
License-File: LICENSE
